railgun/__init__.py
railgun/railgun.py
asyncio_railgun-0.0.1.dist-info/LICENSE
asyncio_railgun-0.0.1.dist-info/METADATA
asyncio_railgun-0.0.1.dist-info/WHEEL
asyncio_railgun-0.0.1.dist-info/top_level.txt
asyncio_railgun-0.0.1.dist-info/RECORD
