Metadata-Version: 2.1
Name: asyncio-railgun
Version: 0.0.1
Summary: Library for easier asyncio concurrent tasks.
Home-page: https://github.com/c-goosen/asyncio-railgun
Author: Christo Goosen
Author-email: christogoosen@gmail.com
License: MIT
Keywords: asyncio concurrent gather tasks
Platform: UNKNOWN
Classifier: Development Status :: 3 - Alpha
Classifier: Intended Audience :: Developers
Classifier: Framework :: AsyncIO
Classifier: Topic :: System :: Networking
Classifier: Natural Language :: English
Classifier: Operating System :: Unix
Classifier: Operating System :: POSIX :: Linux
Classifier: Operating System :: POSIX :: BSD :: FreeBSD
Classifier: Programming Language :: Python
Classifier: Programming Language :: Python :: 3
Classifier: Programming Language :: Python :: 3 :: Only
Classifier: Programming Language :: Python :: 3.4
Classifier: Programming Language :: Python :: 3.5
Classifier: Programming Language :: Python :: 3.6
Classifier: Programming Language :: Python :: 3.7
Classifier: Programming Language :: Python :: 3.8
Classifier: License :: OSI Approved :: MIT License
Classifier: Topic :: Software Development
Classifier: Typing :: Typed
Requires-Python: >=3.6.0
